{
  "personalInformation": {
    "firstName": "Alina",
    "lastName": "Seminiuc",
    "dateOfBirth": "1983-09-06",
    "gender": "Female",
    "idNumber": "1983090612345"
  },
  "triage": {
    "weightKg": 70,
    "heightCm": 165,
    "bmi": 25.7,
    "bloodPressure": "120/75 mmHg",
    "pulse": 78,
    "respiratoryRate": 20,
    "oxygenSaturation": 97
  },
  "consultations": [
    {
      "date": "19/11/2021",
      "complaints": "cefalee, tuse seaca, dispnee la efort fizic moderat, astenie generala marcata, subfebrilitate",
      "medicalHistory": "Nevacinata.  Contactat cu persoana  COVID-19 pozitiva - soțul.",
      "investigationHistory": {
        "laboratory": {
          "fastingBloodSugar": "Unknown",
          "hemoglobin": "Unknown",
          "erythrocytes": "Unknown",
          "leukocytes": "Unknown",
          "proteinaCReactiva": "Unknown"
        },
        "paraclinical": "Rx toracic 25.11.21 - Bilateral leziuni exudativ-interstitiale, leziuni exudativ-alveolare, zone in sticla mata preponderent in campurile pulmonare inferioare. Hilii pulmonari densi. Cord-N; ECG 25.11.21 - Fibrilatie atriala cu FCC 75-105/min. AEC orizontala. Bloc incomplet de ram drept+ Hipertrofie VD (S tip)"
      },
      "physicalExamination": "Tegumentele curate, roz-pale. Edeme periferice absente. Ganglionii limfatici periferici nu se palpeaza. Zgomotele cardiace aritmice. Auscultativ in plamini murmur vezicular diminuat bilateral.",
      "diagnosis": "Infectie prin COVID-19 (forma medie). Pneumonie comunitara bilaterala, etiologie virala, evolutie moderata.",
      "recommendations": "Rederectionata pentru investigatii si tratament."
    }
  ],
  "chronicDiseases": [
    "Diabet zaharat - tratament cu Siofor 500 de 2 ori",
    "Hipertensiune arteriala - tratament cu Indapamid, Ramipril",
    "Fibrilatie atriala - tratament cu Bisoprolol, Amiodoron" 
  ],
  "allergies": ["Nicio alergie cunoscuta"],
  "epidemiologicalHistory": [
    {
      "covid": "19.11.2021",
      "vaccination": "Nevacinat",
      "covidTest": "Pozitiv 19.11.2021"
    }
  ],
  "riskFactors": [
    "Contact cu pacient COVID-19 (sotul)"
  ],
  "previousDiseases": [
    "Nicio boala prealabila cunoscuta"
  ]
}
